spark_eventlog_mcp/__init__.py
spark_eventlog_mcp/server.py
spark_eventlog_mcp/core/mature_data_loader.py
spark_eventlog_mcp/models/__init__.py
spark_eventlog_mcp/models/mature_models.py
spark_eventlog_mcp/models/schemas.py
spark_eventlog_mcp/tools/__init__.py
spark_eventlog_mcp/tools/mature_analyzer.py
spark_eventlog_mcp/tools/mature_report_generator.py
spark_eventlog_mcp/utils/__init__.py
spark_eventlog_mcp/utils/helpers.py
spark_eventlog_mcp-0.1.0.dist-info/licenses/LICENSE
spark_eventlog_mcp-0.1.0.dist-info/METADATA
spark_eventlog_mcp-0.1.0.dist-info/WHEEL
spark_eventlog_mcp-0.1.0.dist-info/entry_points.txt
spark_eventlog_mcp-0.1.0.dist-info/top_level.txt
spark_eventlog_mcp-0.1.0.dist-info/RECORD
