Metadata-Version: 2.4
Name: spark-eventlog-mcp
Version: 0.1.0
Summary: A comprehensive Spark event log analysis MCP server with performance monitoring and optimization recommendations
Author-email: Spark Analytics Team <team@example.com>
License: MIT
Project-URL: Homepage, https://github.com/yhyyz/spark-eventlog-mcp
Project-URL: Repository, https://github.com/yhyyz/spark-eventlog-mcp
Project-URL: Documentation, https://github.com/yhyyz/spark-eventlog-mcp#readme
Project-URL: Bug Reports, https://github.com/yhyyz/spark-eventlog-mcp/issues
Keywords: spark,eventlog,analysis,mcp,performance,monitoring
Classifier: Development Status :: 4 - Beta
Classifier: Intended Audience :: Developers
Classifier: Intended Audience :: System Administrators
Classifier: Topic :: Software Development :: Libraries :: Python Modules
Classifier: Topic :: System :: Monitoring
Classifier: Topic :: System :: Distributed Computing
Classifier: License :: OSI Approved :: MIT License
Classifier: Programming Language :: Python :: 3
Classifier: Programming Language :: Python :: 3.12
Classifier: Operating System :: OS Independent
Requires-Python: >=3.12
License-File: LICENSE
Requires-Dist: fastmcp>=2.0.0
Requires-Dist: pydantic>=2.0.0
Requires-Dist: aiofiles
Requires-Dist: httpx
Requires-Dist: boto3
Requires-Dist: botocore
Requires-Dist: pandas
Requires-Dist: numpy
Requires-Dist: plotly
Requires-Dist: jinja2
Requires-Dist: fastapi>=0.123.9
Requires-Dist: aiohttp>=3.13.2
Dynamic: license-file
